agentdns/__init__.py
agentdns/async_client.py
agentdns/client.py
agentdns/exceptions.py
agentdns/models.py
agentdns/py.typed
agentdns-0.1.0.dist-info/licenses/LICENSE
agentdns-0.1.0.dist-info/METADATA
agentdns-0.1.0.dist-info/WHEEL
agentdns-0.1.0.dist-info/top_level.txt
agentdns-0.1.0.dist-info/RECORD
