Metadata-Version: 2.4
Name: agentdns
Version: 0.1.0
Summary: Python SDK for AgentDNS - Service naming and discovery system for LLM Agents
Author-email: Enfang Cui <enfangcui@gmail.com>, Zhiyuan Liang <liangzy512@gmail.com>
License: Apache-2.0
Project-URL: Homepage, https://github.com/agentdns/agentdns-sdk
Project-URL: Repository, https://github.com/agentdns/agentdns-sdk.git
Keywords: agentdns,llm,agent,service-discovery,dns,ai
Classifier: Development Status :: 4 - Beta
Classifier: Intended Audience :: Developers
Classifier: License :: OSI Approved :: Apache Software License
Classifier: Operating System :: OS Independent
Classifier: Programming Language :: Python :: 3
Classifier: Programming Language :: Python :: 3.8
Classifier: Programming Language :: Python :: 3.9
Classifier: Programming Language :: Python :: 3.10
Classifier: Programming Language :: Python :: 3.11
Classifier: Programming Language :: Python :: 3.12
Classifier: Topic :: Software Development :: Libraries :: Python Modules
Classifier: Topic :: Internet :: Name Service (DNS)
Classifier: Topic :: Scientific/Engineering :: Artificial Intelligence
Classifier: Topic :: Software Development :: Libraries :: Application Frameworks
Requires-Python: >=3.8
License-File: LICENSE
Requires-Dist: requests>=2.25.0
Requires-Dist: aiohttp>=3.8.0
Requires-Dist: pydantic>=2.0.0
Requires-Dist: typing-extensions>=4.0.0
Dynamic: license-file
